stsf/__init__.py
stsf/stsf.py
stsf-0.1.10.dist-info/METADATA
stsf-0.1.10.dist-info/WHEEL
stsf-0.1.10.dist-info/top_level.txt
stsf-0.1.10.dist-info/RECORD
