Metadata-Version: 2.1
Name: stsf
Version: 0.1.10
Summary: A Python module for troubleshooting Apache Solr installations
Home-page: https://github.com/lilocruz/solr-troubleshooting-framework
Author: Michael Cruz Sanchez
Author-email: superlinux.michael5@gmail.com
License: GPLv3
Keywords: Solr,Python,Troubleshoot,Framework,lilocruz,Cli,Apache
Classifier: Development Status :: 3 - Alpha
Classifier: Intended Audience :: System Administrators
Classifier: Intended Audience :: Developers
Classifier: Operating System :: POSIX :: Linux
Classifier: License :: OSI Approved :: GNU General Public License v3 (GPLv3)
Classifier: Programming Language :: Python :: 3
Classifier: Programming Language :: Python :: 3.6
Classifier: Programming Language :: Python :: 3.7
Classifier: Programming Language :: Python :: 3.8
Classifier: Programming Language :: Python :: 3.9
Classifier: Programming Language :: Python :: 3.10
Requires-Dist: requests
